cv_tda-1.0.2.dist-info/licenses/LICENSE
cvtda/autoencoder/Autoencoder.py
cvtda/autoencoder/__init__.py
cvtda/autoencoder/estimate_quality.py
cvtda/autoencoder/try_autoencoders.py
cvtda/classification/MultiImageClassifier.py
cvtda/classification/NNClassifier.py
cvtda/classification/__init__.py
cvtda/classification/classify.py
cvtda/classification/estimate_quality.py
cvtda/classification/information_value.py
cvtda/dumping/__init__.py
cvtda/dumping/base.py
cvtda/dumping/devnull.py
cvtda/dumping/dump_name_concat.py
cvtda/dumping/numpy.py
cvtda/face_recognition/BaseLearner.py
cvtda/face_recognition/DiagramsLearner.py
cvtda/face_recognition/NNLearner.py
cvtda/face_recognition/SimpleTopologicalLearner.py
cvtda/face_recognition/__init__.py
cvtda/face_recognition/learn.py
cvtda/logging/__init__.py
cvtda/logging/base.py
cvtda/logging/cli.py
cvtda/logging/devnull.py
cvtda/neural_network/Dataset.py
cvtda/neural_network/NNBase.py
cvtda/neural_network/__init__.py
cvtda/neural_network/device.py
cvtda/segmentation/Dataset.py
cvtda/segmentation/MiniUnet.py
cvtda/segmentation/__init__.py
cvtda/segmentation/estimate_quality.py
cvtda/segmentation/segment.py
cvtda/segmentation/impl/__init__.py
cvtda/segmentation/impl/bottom.py
cvtda/segmentation/impl/conv.py
cvtda/segmentation/impl/downsample.py
cvtda/segmentation/impl/unet_module.py
cvtda/segmentation/impl/upsample.py
cvtda/topology/DiagramVectorizer.py
cvtda/topology/FeatureExtractor.py
cvtda/topology/FiltrationsExtractor.py
cvtda/topology/GeometryExtractor.py
cvtda/topology/GreyscaleExtractor.py
cvtda/topology/PointCloudsExtractor.py
cvtda/topology/__init__.py
cvtda/topology/interface/Extractor.py
cvtda/topology/interface/TopologicalExtractor.py
cvtda/topology/interface/__init__.py
cvtda/topology/utils/__init__.py
cvtda/topology/utils/hstack.py
cvtda/topology/utils/process_iter.py
cvtda/topology/utils/process_iter_dump.py
cvtda/utils/FeatureExtractorBase.py
cvtda/utils/__init__.py
cvtda/utils/duplicates.py
cvtda/utils/image2pointcloud.py
cvtda/utils/parallel.py
cv_tda-1.0.2.dist-info/METADATA
cv_tda-1.0.2.dist-info/WHEEL
cv_tda-1.0.2.dist-info/top_level.txt
cv_tda-1.0.2.dist-info/RECORD
