Metadata-Version: 2.4
Name: cv-tda
Version: 1.0.2
Summary: A Library to Solve Various Computer Vision Problems Using Topological Data Analysis
Author-email: Aleksandr Abramov <ggttpo100ajiex@yandex.ru>
License-Expression: MIT
Project-URL: Repository, https://github.com/TTPO100AJIEX/CVTDA
Keywords: topological data analysis,computer vision,algebraic topology,image analysis,classification,face recognition,topological features
Classifier: Development Status :: 4 - Beta
Classifier: Intended Audience :: Science/Research
Classifier: Intended Audience :: Developers
Classifier: Operating System :: OS Independent
Classifier: Programming Language :: Python :: 3.10
Classifier: Topic :: Scientific/Engineering
Classifier: Topic :: Scientific/Engineering :: Image Processing
Requires-Python: <3.11,>=3.10
License-File: LICENSE
Requires-Dist: giotto-tda
Requires-Dist: gudhi
Requires-Dist: joblib
Requires-Dist: scikit-learn>=1.4
Requires-Dist: scikit-image
Requires-Dist: tqdm
Requires-Dist: numpy
Provides-Extra: classification
Requires-Dist: catboost; extra == "classification"
Requires-Dist: xgboost; extra == "classification"
Requires-Dist: matplotlib; extra == "classification"
Requires-Dist: pandas; extra == "classification"
Requires-Dist: torch; extra == "classification"
Requires-Dist: torchvision; extra == "classification"
Provides-Extra: facerecognition
Requires-Dist: pytorch-metric-learning; extra == "facerecognition"
Requires-Dist: faiss-cpu; extra == "facerecognition"
Requires-Dist: matplotlib; extra == "facerecognition"
Requires-Dist: torch; extra == "facerecognition"
Requires-Dist: torchvision; extra == "facerecognition"
Provides-Extra: autoencoder
Requires-Dist: pandas; extra == "autoencoder"
Requires-Dist: torch; extra == "autoencoder"
Provides-Extra: segmentation
Requires-Dist: pandas; extra == "segmentation"
Requires-Dist: torch; extra == "segmentation"
Requires-Dist: segmentation-models-pytorch; extra == "segmentation"
Dynamic: license-file
